gleenai/__init__.py
gleenai/api.py
gleenai-1.0.0.dist-info/METADATA
gleenai-1.0.0.dist-info/WHEEL
gleenai-1.0.0.dist-info/top_level.txt
gleenai-1.0.0.dist-info/RECORD
